yaws/__init__.py
yaws/yaws.py
yaws-1.3.0.dist-info/LICENSE
yaws-1.3.0.dist-info/METADATA
yaws-1.3.0.dist-info/WHEEL
yaws-1.3.0.dist-info/entry_points.txt
yaws-1.3.0.dist-info/top_level.txt
yaws-1.3.0.dist-info/RECORD
