Metadata-Version: 2.1
Name: yaws
Version: 1.3.0
Summary: Utils for AWS cloud
Home-page: https://github.com/loopingz/yaws
Author: Loopingz
Author-email: loopingz@loopingz.com
License: LGPL-3
Keywords: aws tools
Platform: UNKNOWN
Classifier: Development Status :: 4 - Beta
Classifier: Topic :: Software Development :: Build Tools
Classifier: License :: OSI Approved :: GNU Lesser General Public License v3 (LGPLv3)
Classifier: Programming Language :: Python :: 2
Classifier: Programming Language :: Python :: 2.6
Classifier: Programming Language :: Python :: 2.7
Classifier: Programming Language :: Python :: 3
Classifier: Programming Language :: Python :: 3.2
Classifier: Programming Language :: Python :: 3.3
Classifier: Programming Language :: Python :: 3.4
Requires-Python: >=2.6
Requires-Dist: boto3
